auto_update/__init__.py
auto_update_by_hamu-0.0.5.dist-info/LICENSE
auto_update_by_hamu-0.0.5.dist-info/METADATA
auto_update_by_hamu-0.0.5.dist-info/WHEEL
auto_update_by_hamu-0.0.5.dist-info/top_level.txt
auto_update_by_hamu-0.0.5.dist-info/RECORD
