Metadata-Version: 2.1
Name: auto-update-by-hamu
Version: 0.0.5
Summary: A small example package
Author-email: hamusuta <2326955513@qq.com>
Project-URL: Homepage, https://gitee.com/hamusuta/python_auto_update
Project-URL: Bug Tracker, https://gitee.com/hamusuta/python_auto_update/issues
Classifier: Programming Language :: Python :: 3
Classifier: License :: OSI Approved :: MIT License
Classifier: Operating System :: OS Independent
Requires-Python: >=3.7
License-File: LICENSE
